html_to_etree/__init__.py
html_to_etree-0.2.0.dist-info/DESCRIPTION.rst
html_to_etree-0.2.0.dist-info/METADATA
html_to_etree-0.2.0.dist-info/RECORD
html_to_etree-0.2.0.dist-info/WHEEL
html_to_etree-0.2.0.dist-info/metadata.json
html_to_etree-0.2.0.dist-info/top_level.txt
