Metadata-Version: 1.1
Name: html-to-etree
Version: 0.2.0
Summary: parse html to etree
Home-page: https://github.com/fluquid/html-to-etree
Author: Johannes Ahlmann
Author-email: johannes@fluquid.com
License: BSD-3-Clause
Keywords: html-to-etree
Platform: UNKNOWN
Classifier: Development Status :: 2 - Pre-Alpha
Classifier: Intended Audience :: Developers
Classifier: License :: OSI Approved :: MIT License
Classifier: Natural Language :: English
Classifier: Programming Language :: Python :: 2
Classifier: Programming Language :: Python :: 2.7
Classifier: Programming Language :: Python :: 3
Classifier: Programming Language :: Python :: 3.4
Classifier: Programming Language :: Python :: 3.5
